odoo/addons/delivery_schenker_picking_volume/README.rst
odoo/addons/delivery_schenker_picking_volume/__init__.py
odoo/addons/delivery_schenker_picking_volume/__manifest__.py
odoo/addons/delivery_schenker_picking_volume/i18n/delivery_schenker_picking_volume.pot
odoo/addons/delivery_schenker_picking_volume/models/__init__.py
odoo/addons/delivery_schenker_picking_volume/models/delivery_carrier.py
odoo/addons/delivery_schenker_picking_volume/readme/CONTRIBUTORS.rst
odoo/addons/delivery_schenker_picking_volume/readme/DESCRIPTION.rst
odoo/addons/delivery_schenker_picking_volume/static/description/icon.png
odoo/addons/delivery_schenker_picking_volume/static/description/index.html
odoo/addons/delivery_schenker_picking_volume/tests/__init__.py
odoo/addons/delivery_schenker_picking_volume/tests/test_delivery_schenker.py
odoo14_addon_delivery_schenker_picking_volume-14.0.1.2.0.dist-info/METADATA
odoo14_addon_delivery_schenker_picking_volume-14.0.1.2.0.dist-info/WHEEL
odoo14_addon_delivery_schenker_picking_volume-14.0.1.2.0.dist-info/top_level.txt
odoo14_addon_delivery_schenker_picking_volume-14.0.1.2.0.dist-info/RECORD
