Metadata-Version: 2.1
Name: odoo14-addon-delivery-schenker-picking-volume
Version: 14.0.1.2.0
Summary: Glue module between delivery_schenker and stock_picking_volumeWith this module the transmitted volume is changed,it uses the computed volume from stock_picking_volume
Home-page: https://github.com/OCA/delivery-carrier
Author: MT Software, Odoo Community Association (OCA)
Author-email: support@odoo-community.org
License: AGPL-3
Platform: UNKNOWN
Classifier: Programming Language :: Python
Classifier: Framework :: Odoo
Classifier: Framework :: Odoo :: 14.0
Classifier: License :: OSI Approved :: GNU Affero General Public License v3
Requires-Python: >=3.6
Requires-Dist: odoo14-addon-delivery-schenker
Requires-Dist: odoo14-addon-stock-picking-volume
Requires-Dist: odoo (<14.1dev,>=14.0a)
